wiggum/__init__.py
wiggum/__main__.py
wiggum/agents.py
wiggum/agents_claude.py
wiggum/agents_codex.py
wiggum/agents_gemini.py
wiggum/cli.py
wiggum/config.py
wiggum/parsing.py
wiggum/py.typed
wiggum/runner.py
wiggum/tasks.py
wiggum/templates/LOOP-PROMPT.md
wiggum/templates/META-PROMPT.md
wiggum/templates/TASKS.md
wiggum-0.1.3.dist-info/WHEEL
wiggum-0.1.3.dist-info/entry_points.txt
wiggum-0.1.3.dist-info/METADATA
wiggum-0.1.3.dist-info/RECORD
