Metadata-Version: 2.4
Name: wiggum
Version: 0.1.3
Summary: Ralph Wiggum loop for agents
Keywords: ai-agents,automation,claude,codex,gemini,loop,task-runner
Author: YY Ahn
Author-email: YY Ahn <yongyeol@gmail.com>
License-Expression: MIT
Classifier: Development Status :: 4 - Beta
Classifier: Environment :: Console
Classifier: Intended Audience :: Developers
Classifier: License :: OSI Approved :: MIT License
Classifier: Operating System :: OS Independent
Classifier: Programming Language :: Python :: 3
Classifier: Programming Language :: Python :: 3.12
Classifier: Programming Language :: Python :: 3.13
Classifier: Topic :: Software Development :: Build Tools
Classifier: Topic :: Software Development :: Quality Assurance
Requires-Dist: typer>=0.9.0
Requires-Dist: tomli>=2.0.0 ; python_full_version < '3.11'
Requires-Dist: tomli-w>=1.0.0
Requires-Python: >=3.12
Project-URL: Homepage, https://github.com/yy/wiggum
Project-URL: Issues, https://github.com/yy/wiggum/issues
Project-URL: Repository, https://github.com/yy/wiggum
